py_sugo/__init__.py
py_sugo/application.py
py_sugo/core.py
py_sugo/example.py
py_sugo/http_client.py
py_sugo/middleware.py
py_sugo/parsing.py
py_sugo/request.py
py_sugo/response.py
py_sugo/router.py
py_sugo/server.py
py_sugo-0.1.0.dist-info/WHEEL
py_sugo-0.1.0.dist-info/METADATA
py_sugo-0.1.0.dist-info/RECORD
